abmatrix/__init__.py
abmatrix/abmatrix.py
abmatrix-0.3.3.dist-info/METADATA
abmatrix-0.3.3.dist-info/WHEEL
abmatrix-0.3.3.dist-info/top_level.txt
abmatrix-0.3.3.dist-info/RECORD
