Metadata-Version: 2.1
Name: abmatrix
Version: 0.3.3
Summary: Python module to read and parse AB Matrix files
Author-email: Daniel Garrigan <popgendad@proton.me>
Project-URL: Homepage, https://github.com/wisdomhealth-inc/abmatrix
Classifier: Programming Language :: Python :: 3
Classifier: Operating System :: OS Independent
Requires-Python: >=3.7
